googlehomepush/__init__.py
googlehomepush/googlecloudTTS.py
googlehomepush/googletts.py
googlehomepush/http_server.py
googlehomepush-0.1.0.dist-info/LICENSE
googlehomepush-0.1.0.dist-info/METADATA
googlehomepush-0.1.0.dist-info/WHEEL
googlehomepush-0.1.0.dist-info/top_level.txt
googlehomepush-0.1.0.dist-info/RECORD
