Metadata-Version: 2.1
Name: googlehomepush
Version: 0.1.0
Summary: library to push text message or sond to Google Home.
Home-page: https://github.com/deblockt/google-home-push
Author: Thomas Deblock
Author-email: deblock.thomas.62@gmail.com
License: UNKNOWN
Platform: UNKNOWN
Classifier: Programming Language :: Python :: 3
Classifier: License :: OSI Approved :: MIT License
Classifier: Operating System :: OS Independent
Requires-Dist: gTTS (==2.0.3)
Requires-Dist: pychromecast (==2.3.0)
Requires-Dist: google-cloud-texttospeech (==0.2.0)
Requires-Dist: gtts-token (~=1.1.3)
